kleenlogger/__about__.py
kleenlogger/__init__.py
kleenlogger/kleenlogger.py
KleenLogger-0.1.2.dist-info/LICENSE
KleenLogger-0.1.2.dist-info/METADATA
KleenLogger-0.1.2.dist-info/WHEEL
KleenLogger-0.1.2.dist-info/top_level.txt
KleenLogger-0.1.2.dist-info/RECORD
