Metadata-Version: 2.1
Name: KleenLogger
Version: 0.1.2
Summary: Clean Logger system for python application.
Home-page: UNKNOWN
Author: Edenskull
License: MIT
Platform: UNKNOWN
Classifier: Programming Language :: Python :: 3
Classifier: Programming Language :: Python :: 3.7
Classifier: Intended Audience :: Developers
Classifier: License :: OSI Approved :: MIT License
Classifier: Operating System :: OS Independent
